monkeywork/__init__.py
monkeywork/monkeywork.py
monkeywork-0.1.3.dist-info/LICENCE
monkeywork-0.1.3.dist-info/METADATA
monkeywork-0.1.3.dist-info/WHEEL
monkeywork-0.1.3.dist-info/top_level.txt
monkeywork-0.1.3.dist-info/RECORD
