Metadata-Version: 2.1
Name: monkeywork
Version: 0.1.3
Summary: Write and edit random files in a given directory
Home-page: https://github.com/pylomatic/monkeywork
Author: Pylomatic
Author-email: pylomatic@conelab.ch
Classifier: Programming Language :: Python :: 3
Classifier: License :: OSI Approved :: MIT License
Classifier: Operating System :: OS Independent
Requires-Python: >=3.6
License-File: LICENCE
